agentware/__init__.py
agentware/agent.py
agentware/agent_logger.py
agentware/base.py
agentware/core_engines.py
agentware/error_codes.py
agentware/helper_agents.py
agentware/hub.py
agentware/memory.py
agentware/perception.py
agentware/singleton.py
agentware/base_agent_configs/__init__.py
agentware/base_agent_configs/attribute_question.json
agentware/base_agent_configs/conflict_resolver.json
agentware/base_agent_configs/detector.json
agentware/base_agent_configs/extraction.json
agentware/base_agent_configs/facts.json
agentware/base_agent_configs/graph_executor.json
agentware/base_agent_configs/reflection.json
agentware/base_agent_configs/reflection_question.json
agentware/base_agent_configs/summarize.json
agentware/base_agent_configs/tool_query.json
agentware/utils/__init__.py
agentware/utils/num_token_utils.py
agentware/utils/json_fixes/__init__.py
agentware/utils/json_fixes/auto_fix.py
agentware/utils/json_fixes/bracket_termination.py
agentware/utils/json_fixes/escaping.py
agentware/utils/json_fixes/master_json_fix_method.py
agentware/utils/json_fixes/missing_quotes.py
agentware/utils/json_fixes/parsing.py
agentware/utils/json_fixes/utilities.py
agentware/utils/json_validation/__init__.py
agentware/utils/json_validation/validate_json.py
tests/__init__.py
tests/agent_workflow_test.py
tests/config_test.py
tests/connector_test.py
tests/helper_agents_test.py
tests/memory_test.py
tests/prompt_processor_test.py
tests/utils.py
tests/vision_stream_test.py
agentware-1.2.0.dist-info/METADATA
agentware-1.2.0.dist-info/WHEEL
agentware-1.2.0.dist-info/top_level.txt
agentware-1.2.0.dist-info/RECORD
