Metadata-Version: 2.1
Name: agentware
Version: 1.2.0
Summary: A framework that can be used to easily build agents that has memory and knowledgebase
Author: darthjaja
Author-email: your-email@example.com
Requires-Dist: tiktoken (==0.3.3)
Requires-Dist: openai (==0.27.2)
Requires-Dist: jwt (==1.3.1)
Requires-Dist: colorlog (==6.7.0)
Requires-Dist: python-dotenv (==1.0.0)
Requires-Dist: pystache (==0.6.0)
Requires-Dist: ultralytics (==8.0.158)
Requires-Dist: img2vec-pytorch (==1.0.1)
